<?xml version="1.0" encoding="UTF-8"?>
<s>
<name>Coatbridge College</name>
<id>13944</id>
<b2_url>https://coatbridge.blackboard.com/webapps/Bb-mobile-bb_bb60/</b2_url>
<has_community_system>1</has_community_system>
<username_label></username_label>
<has_mobile_central>0</has_mobile_central>
<http_auth>0</http_auth>
<from_people_soft>1</from_people_soft>
<client_id>2010</client_id>
<can_has_ssl_login>true</can_has_ssl_login>
<access><wifi>1</wifi>
<carrier>1</carrier>
<sprint_local>0</sprint_local>
</access>
<people_soft_institution_id>306773</people_soft_institution_id>
<euse>vlesupport@coatbridge.ac.uk</euse>
<euse_label>vlesupport@coatbridge.ac.uk</euse_label>
</s>
